{
	"backtraceGraph" : 
	{
		"commands" : 
		[
			"install"
		],
		"files" : 
		[
			"CMakeLists.txt"
		],
		"nodes" : 
		[
			{
				"file" : 0
			},
			{
				"command" : 0,
				"file" : 0,
				"line" : 250,
				"parent" : 0
			},
			{
				"command" : 0,
				"file" : 0,
				"line" : 267,
				"parent" : 0
			},
			{
				"command" : 0,
				"file" : 0,
				"line" : 288,
				"parent" : 0
			},
			{
				"command" : 0,
				"file" : 0,
				"line" : 299,
				"parent" : 0
			},
			{
				"command" : 0,
				"file" : 0,
				"line" : 328,
				"parent" : 0
			}
		]
	},
	"installers" : 
	[
		{
			"backtrace" : 1,
			"component" : "Unspecified",
			"destination" : "lib",
			"paths" : 
			[
				"lib/Debug/string.lib"
			],
			"targetId" : "string::@6890427a1f51a3e7e1df",
			"targetIndex" : 4,
			"type" : "target"
		},
		{
			"backtrace" : 2,
			"component" : "Unspecified",
			"destination" : "lib/cmake/string",
			"exportName" : "stringTargets",
			"exportTargets" : 
			[
				{
					"id" : "string::@6890427a1f51a3e7e1df",
					"index" : 4
				}
			],
			"paths" : 
			[
				"CMakeFiles/Export/5d8e1d1478a0589079b5955a1059c1d4/stringTargets.cmake"
			],
			"type" : "export"
		},
		{
			"backtrace" : 3,
			"component" : "Unspecified",
			"destination" : "include/string",
			"paths" : 
			[
				"out/build/x64-Debug/include/string/version.hpp"
			],
			"type" : "file"
		},
		{
			"backtrace" : 4,
			"component" : "Unspecified",
			"destination" : "include",
			"paths" : 
			[
				"include/string"
			],
			"type" : "directory"
		},
		{
			"backtrace" : 5,
			"component" : "Unspecified",
			"destination" : "lib/cmake/string",
			"paths" : 
			[
				"out/build/x64-Debug/stringConfig.cmake",
				"out/build/x64-Debug/stringConfigVersion.cmake"
			],
			"type" : "file"
		}
	],
	"paths" : 
	{
		"build" : ".",
		"source" : "."
	}
}
